{
  "schema_version": "1.0",
  "tool": "rsfusa",
  "project": "rust-LIN",
  "asil": "ASIL-B",
  "source": "requirements.json",
  "requirements": [
    {"id": "REQ-LIN-001", "annotation": "//fusa:req REQ-LIN-001"},
    {"id": "REQ-LIN-002", "annotation": "//fusa:req REQ-LIN-002"},
    {"id": "REQ-LIN-003", "annotation": "//fusa:req REQ-LIN-003"},
    {"id": "REQ-LIN-004", "annotation": "//fusa:req REQ-LIN-004"},
    {"id": "REQ-LIN-005", "annotation": "//fusa:req REQ-LIN-005"},
    {"id": "REQ-LIN-006", "annotation": "//fusa:req REQ-LIN-006"},
    {"id": "REQ-LIN-007", "annotation": "//fusa:req REQ-LIN-007"},
    {"id": "REQ-LIN-008", "annotation": "//fusa:req REQ-LIN-008"},
    {"id": "REQ-LIN-009", "annotation": "//fusa:req REQ-LIN-009"},
    {"id": "REQ-LIN-010", "annotation": "//fusa:req REQ-LIN-010"},
    {"id": "REQ-LIN-011", "annotation": "//fusa:req REQ-LIN-011"},
    {"id": "REQ-LIN-012", "annotation": "//fusa:req REQ-LIN-012"},
    {"id": "REQ-LIN-013", "annotation": "//fusa:req REQ-LIN-013"},
    {"id": "REQ-LIN-014", "annotation": "//fusa:req REQ-LIN-014"},
    {"id": "REQ-LIN-015", "annotation": "//fusa:req REQ-LIN-015"},
    {"id": "REQ-LIN-016", "annotation": "//fusa:req REQ-LIN-016"},
    {"id": "REQ-LIN-017", "annotation": "//fusa:req REQ-LIN-017"},
    {"id": "REQ-LIN-018", "annotation": "//fusa:req REQ-LIN-018"},
    {"id": "REQ-LIN-019", "annotation": "//fusa:req REQ-LIN-019"},
    {"id": "REQ-LIN-020", "annotation": "//fusa:req REQ-LIN-020"},
    {"id": "REQ-LIN-021", "annotation": "//fusa:req REQ-LIN-021"},
    {"id": "REQ-VIRT-001", "annotation": "//fusa:req REQ-VIRT-001"},
    {"id": "REQ-VIRT-002", "annotation": "//fusa:req REQ-VIRT-002"},
    {"id": "REQ-VIRT-003", "annotation": "//fusa:req REQ-VIRT-003"},
    {"id": "REQ-VIRT-004", "annotation": "//fusa:req REQ-VIRT-004"},
    {"id": "REQ-VIRT-005", "annotation": "//fusa:req REQ-VIRT-005"},
    {"id": "REQ-VIRT-006", "annotation": "//fusa:req REQ-VIRT-006"},
    {"id": "REQ-VIRT-007", "annotation": "//fusa:req REQ-VIRT-007"},
    {"id": "REQ-VIRT-008", "annotation": "//fusa:req REQ-VIRT-008"},
    {"id": "REQ-VIRT-009", "annotation": "//fusa:req REQ-VIRT-009"},
    {"id": "REQ-VIRT-010", "annotation": "//fusa:req REQ-VIRT-010"},
    {"id": "REQ-VIRT-011", "annotation": "//fusa:req REQ-VIRT-011"},
    {"id": "REQ-VIRT-012", "annotation": "//fusa:req REQ-VIRT-012"},
    {"id": "REQ-MASTER-001", "annotation": "//fusa:req REQ-MASTER-001"},
    {"id": "REQ-MASTER-002", "annotation": "//fusa:req REQ-MASTER-002"},
    {"id": "REQ-MASTER-003", "annotation": "//fusa:req REQ-MASTER-003"},
    {"id": "REQ-MASTER-004", "annotation": "//fusa:req REQ-MASTER-004"},
    {"id": "REQ-MASTER-005", "annotation": "//fusa:req REQ-MASTER-005"},
    {"id": "REQ-SEC-001", "annotation": "//fusa:req REQ-SEC-001"},
    {"id": "REQ-SEC-007", "annotation": "//fusa:req REQ-SEC-007"},
    {"id": "REQ-SEC-008", "annotation": "//fusa:req REQ-SEC-008"}
  ]
}
